{"npc":{"name":"Rolfe Hawthorne","id":1000540,"patch":1.0,"zoneid":55,"coords":[16.73,27.18],"areaid":107,"appearance":{"gender":"Male","race":"Hyur","tribe":"Midlander","height":50,"face":1,"jaw":3,"eyebrows":1,"nose":1,"skinColor":"3, 2","skinColorCode":"#E9C5AD","muscle":50,"hairStyle":131002,"hairColor":"5, 8","hairColorCode":"#443B2E","eyeSize":"Large","eyeShape":2,"eyeColor":"9, 8","eyeColorCode":"#512910","mouth":3,"facialfeatures":[131111,131112],"facialfeatureColor":"1, 1","facialfeatureColorCode":"#F7F7F7"},"quests":[66245,66246,66251,66793],"equipment":[{"id":6281,"uncertainty":1},{"id":3500,"uncertainty":1},{"id":3885,"uncertainty":1}]},"partials":[{"type":"quest","id":"66245","obj":{"i":66245,"n":"Ein Tänzchen in Ehren","g":1,"l":55,"s":115}},{"type":"quest","id":"66246","obj":{"i":66246,"n":"Gastgeschenke","g":1,"l":55,"s":116}},{"type":"quest","id":"66251","obj":{"i":66251,"n":"Ein kühler Empfang","g":1,"l":55,"s":117}},{"type":"quest","id":"66793","obj":{"i":66793,"n":"Geschenkt ist geschenkt","g":26,"l":55,"s":0,"r":1}},{"type":"item","id":"6281","obj":{"i":6281,"n":"Hopliten-Wappenrock","l":60,"c":1433,"t":35}},{"type":"item","id":"3500","obj":{"i":3500,"n":"Gryphenleder-Kecks","l":70,"c":1751,"t":36}},{"type":"item","id":"3885","obj":{"i":3885,"n":"Raptorleder-Kniestiefel","l":46,"c":2120,"t":38,"p":5481}}]}