{"npc":{"name":"Bloezoeng","id":1006975,"patch":2.2,"zoneid":67,"coords":[22.16,8.78],"areaid":943,"appearance":{"gender":"Male","race":"Roegadyn","tribe":"Sea Wolf","height":75,"face":2,"jaw":3,"eyebrows":3,"nose":4,"skinColor":"11, 7","skinColorCode":"#4C504D","muscle":100,"hairStyle":135008,"hairColor":"4, 4","hairColorCode":"#E7C585","highlightColor":"17, 8","highlightColorCode":"#2C141B","eyeSize":"Small","eyeShape":4,"eyeColor":"24, 6","eyeColorCode":"#6E763E","mouth":3,"facialfeatures":[135121,135122,135123,135125],"facialfeatureColor":"1, 1","facialfeatureColorCode":"#F7F7F7"},"quests":[65630,65967,66947,67062,68722],"talk":[{"questid":65630,"lines":["Hunger's not the best sauce, by the onion, but hard work! And none work harder than adventurers, I say.","Whatever company we kept then, we're cooks now and proud of it. Aye, no snow-lined ways for us!","A shame he has to spend his days feeding wealthy ingrates, whereas I get to feed honest folk."]}],"equipment":[{"id":2497},{"id":2727,"dye":12},{"id":6972,"dye":12,"uncertainty":1},{"id":3488,"dye":12},{"id":3885,"uncertainty":1}]},"partials":[{"type":"quest","id":"65630","obj":{"i":65630,"n":"Glibberiges Scheusal","g":58,"l":67,"s":510,"f":1}},{"type":"quest","id":"65967","obj":{"i":65967,"n":"Es ist nicht leicht, grün zu sein","g":58,"l":67,"s":520,"f":1}},{"type":"quest","id":"66947","obj":{"i":66947,"n":"Dem Käse die Freiheit","g":58,"l":67,"s":500,"f":1}},{"type":"quest","id":"67062","obj":{"i":67062,"n":"Rauschebarts Geheimnis","g":58,"l":67,"s":500,"f":1}},{"type":"quest","id":"68722","obj":{"i":68722,"n":"Das Salz in der Suppe","g":58,"l":67,"s":10040}},{"type":"item","id":"2497","obj":{"i":2497,"n":"Anfänger-Kasserolle","l":19,"c":817,"t":26,"p":732}},{"type":"item","id":"2727","obj":{"i":2727,"n":"Samtbandana","l":23,"c":1007,"t":34,"p":665}},{"type":"item","id":"6972","obj":{"i":6972,"n":"Valention-Schürze","l":1,"c":4187,"t":35,"p":59}},{"type":"item","id":"3488","obj":{"i":3488,"n":"Gourmet-Strumpfhose","l":55,"c":1739,"t":36}},{"type":"item","id":"3885","obj":{"i":3885,"n":"Raptorleder-Kniestiefel","l":46,"c":2120,"t":38,"p":5481}}]}