{"npc":{"name":"Leidend[a] Mann","id":1014356,"patch":3.0,"zoneid":2001,"coords":[12.26,19.27],"areaid":2069,"appearance":{"gender":"Male","race":"Elezen","tribe":"Wildwood","height":25,"face":3,"jaw":2,"eyebrows":1,"nose":4,"skinColor":"2, 4","skinColorCode":"#D0A586","hairStyle":132001,"hairColor":"8, 4","hairColorCode":"#D08E55","eyeSize":"Large","eyeShape":6,"eyeColor":"19, 5","eyeColorCode":"#344568","mouth":4,"extraFeatureName":"Ears","extraFeatureShape":1,"extraFeatureSize":50},"quests":[67490],"equipment":[{"id":1855},{"id":3164,"uncertainty":1},{"id":3673,"uncertainty":1},{"id":9946},{"id":6731,"uncertainty":2}]},"partials":[{"type":"quest","id":"67490","obj":{"i":67490,"n":"Erste Opfer","g":64,"l":2082,"s":5821}},{"type":"item","id":"1855","obj":{"i":1855,"n":"Mithrillanze","l":40,"c":310,"t":5,"p":7776}},{"type":"item","id":"3164","obj":{"i":3164,"n":"Restaurierter Schuppenpanzer","l":44,"c":1427,"t":35}},{"type":"item","id":"3673","obj":{"i":3673,"n":"Sipahi-Handschuhe","l":55,"c":1916,"t":37}},{"type":"item","id":"9946","obj":{"i":9946,"n":"Knappen-Reiterhose","l":100,"c":5671,"t":36}},{"type":"item","id":"6731","obj":{"i":6731,"n":"Leggins der Strenge","l":60,"c":4108,"t":38}}]}