{"npc":{"name":"Weidheri","id":1020871,"patch":4.0,"zoneid":2407,"coords":[16.74,36.35],"areaid":2660,"appearance":{"gender":"Male","race":"Hyur","tribe":"Highlander","height":50,"face":4,"customFace":1,"jaw":1,"eyebrows":2,"nose":3,"skinColor":"24, 5","skinColorCode":"#906955","muscle":50,"hairStyle":131512,"hairColor":"1, 8","hairColorCode":"#121212","eyeSize":"Large","eyeShape":4,"eyeColor":"5, 8","eyeColorCode":"#5E4524","mouth":3,"facepaint":130106,"facepaintShade":"Dark","facepaintColor":"1, 8","facepaintColorCode":"#000000","facialfeatures":[131642],"facialfeatureColor":"1, 1","facialfeatureColorCode":"#F7F7F7"},"quests":[68366,68374,68378,68398,68574],"talk":[{"questid":68069,"lines":["You're looking parched, friend. How's about stopping by my tavern to put back a few?","If you ever need a drink, stop by my pub any time you like for one on the house. Any friend of the Resistance is a friend of mine."]}],"equipment":[{"id":3187,"uncertainty":1},{"id":3309},{"id":9302,"uncertainty":6}]},"partials":[{"type":"quest","id":"68366","obj":{"i":68366,"n":"Man gönnt sich ja sonst nichts","g":68,"l":2407,"s":8050}},{"type":"quest","id":"68374","obj":{"i":68374,"n":"Knackige Beine","g":68,"l":2407,"s":8060}},{"type":"quest","id":"68378","obj":{"i":68378,"n":"Ein guter Garlear","g":68,"l":2407,"s":8170,"f":1}},{"type":"quest","id":"68398","obj":{"i":68398,"n":"Erarts Spur","g":68,"l":2407,"s":9060}},{"type":"quest","id":"68574","obj":{"i":68574,"n":"Wie man sich bettet","g":19,"l":2406,"s":3,"f":1}},{"type":"quest","id":"68069","obj":{"i":68069,"n":"Zeit zu rasten, Zeit zu sinnieren","g":6,"l":2406,"s":930}},{"type":"item","id":"3187","obj":{"i":3187,"n":"Wollkittel","l":46,"c":1450,"t":35,"p":5344}},{"type":"item","id":"3309","obj":{"i":3309,"n":"Hanf-Chausses","l":5,"c":1570,"t":36,"p":94}},{"type":"item","id":"9302","obj":{"i":9302,"n":"Kunsthandwerker-Sandalen","l":60,"c":5519,"t":38}}]}