{"instance":{"name":"機工城アレキサンダー：天動編4","category":"レイド","description":"中央管制室に突入し、ラウンドロクスを救出した光の戦士たち。しかし、クイックシンクスは奥の手とばかりに、自らの力で「エニグマ・コーデックス」を操作してみせる。こうなっては、アレキサンダーの中枢へと直接乗り込み、動力源となっているコアを停止するしかない。「時」を巡る戦いは、ついに最終局面へと移行する！","id":30042,"patch":3.4,"categoryIcon":61802,"time":90,"min_lvl":60,"fullIcon":112191,"healer":2,"tank":2,"ranged":2,"melee":2,"max_lvl":60,"min_ilvl":230,"fights":[{"currency":[{"id":28,"amount":20}],"type":"Boss","coffer":{"items":[16548,16549,16547,16574]},"mobs":[61580000005193]}],"rewards":[16545,16766],"currency":[{"id":28,"amount":20}],"unlockedByQuest":67874},"partials":[{"type":"item","id":"16548","obj":{"i":16548,"n":"アレキサンダークランク","l":250,"c":8946,"t":61}},{"type":"item","id":"16549","obj":{"i":16549,"n":"アレキサンダースプリング","l":250,"c":8947,"t":61}},{"type":"item","id":"16547","obj":{"i":16547,"n":"アレキサンダーシャフト","l":250,"c":8945,"t":61}},{"type":"item","id":"16574","obj":{"i":16574,"n":"ミニアレキサンダー","l":1,"c":8959,"t":81}},{"type":"mob","id":"61580000005193","obj":{"i":61580000005193,"n":"アレキサンダー・プライム","l":"60","z":1853,"t":null}},{"type":"item","id":"16545","obj":{"i":16545,"n":"アレキサンダーの歯車","l":260,"c":8943,"t":61}},{"type":"item","id":"16766","obj":{"i":16766,"n":"カード:アレキサンダー・プライム","l":1,"c":5780,"t":86}},{"type":"quest","id":"67874","obj":{"i":67874,"n":"聖なる審判","g":11,"l":2001,"s":14,"f":1}}]}