{"npc":{"name":"Gisilbehrt","id":1006217,"patch":1.0,"title":"Flame Commander","zoneid":45,"coords":[17.88,13.45],"areaid":313,"appearance":{"gender":"Male","race":"Hyur","tribe":"Highlander","height":50,"face":1,"jaw":3,"eyebrows":4,"nose":4,"skinColor":"19, 7","skinColorCode":"#5F4231","muscle":50,"hairStyle":131508,"hairColor":"1, 7","hairColorCode":"#333333","eyeSize":"Large","eyeShape":5,"eyeColor":"23, 8","eyeColorCode":"#313A24","mouth":3},"quests":[66297,66298,66753,66756],"equipment":[{"id":2867,"uncertainty":1},{"id":3147,"uncertainty":1},{"id":13693,"uncertainty":1},{"id":3449,"uncertainty":1},{"id":3900,"uncertainty":1}]},"partials":[{"type":"quest","id":"66297","obj":{"i":66297,"n":"Tea for Three","g":1,"l":45,"s":138}},{"type":"quest","id":"66298","obj":{"i":66298,"n":"Foot in the Door","g":1,"l":45,"s":139}},{"type":"quest","id":"66753","obj":{"i":66753,"n":"Peace for Thanalan","g":23,"l":51,"s":0,"f":1}},{"type":"quest","id":"66756","obj":{"i":66756,"n":"An Eye on the Inside","g":23,"l":45,"s":0,"f":1}},{"type":"item","id":"2867","obj":{"i":2867,"n":"Sipahi Turban","l":55,"c":1142,"t":34}},{"type":"item","id":"3147","obj":{"i":3147,"n":"Woolen Shirt","l":40,"c":1411,"t":35,"p":4212}},{"type":"item","id":"13693","obj":{"i":13693,"n":"Scion Thief's Halfgloves","l":1,"c":7874,"t":37}},{"type":"item","id":"3449","obj":{"i":3449,"n":"Sipahi Sarouel","l":55,"c":1700,"t":36}},{"type":"item","id":"3900","obj":{"i":3900,"n":"Sipahi Crakows","l":55,"c":2134,"t":38}}]}