{"npc":{"name":"Ahlduwil","id":1006505,"patch":1.0,"zoneid":33,"coords":[17.49,31.57],"areaid":461,"appearance":{"gender":"Male","race":"Roegadyn","tribe":"Sea Wolf","height":25,"face":2,"jaw":2,"eyebrows":2,"nose":6,"skinColor":"7, 3","skinColorCode":"#B7C8B3","muscle":50,"hairStyle":135007,"hairColor":"1, 7","hairColorCode":"#333333","eyeSize":"Large","eyeShape":2,"eyeColor":"1, 1","eyeColorCode":"#F7F7F7","mouth":3},"quests":[66499,66501],"talk":[{"lines":["Pish on the sheven hells and choke on the shteam! Was <span class=\"emphasis\">shupposed</span> to be easy. Wine...wine by the caskful and...mead...beer too, of course, beer too. Warn't shupposed to be no <span class=\"emphasis\">real</span> shpi-spirits, ye see?"]}],"equipment":[{"id":1754},{"id":2721},{"id":3218,"uncertainty":1},{"id":3540},{"id":3440,"uncertainty":6},{"id":3906,"uncertainty":2}]},"partials":[{"type":"quest","id":"66499","obj":{"i":66499,"n":"Sweet Somethings","g":1,"l":33,"s":220}},{"type":"quest","id":"66501","obj":{"i":66501,"n":"Pickled and Brined","g":54,"l":33,"s":420}},{"type":"item","id":"1754","obj":{"i":1754,"n":"Iron War Axe","l":15,"c":220,"t":3,"p":744}},{"type":"item","id":"2721","obj":{"i":2721,"n":"Doctore's Chain Coif","l":22,"c":1003,"t":34}},{"type":"item","id":"3218","obj":{"i":3218,"n":"Vintage Haubergeon","l":49,"c":1480,"t":35}},{"type":"item","id":"3540","obj":{"i":3540,"n":"Bronze Mitt Gauntlets","l":12,"c":1789,"t":37,"p":376}},{"type":"item","id":"3440","obj":{"i":3440,"n":"Flame Sergeant's Skirt","l":46,"c":1691,"t":36}},{"type":"item","id":"3906","obj":{"i":3906,"n":"Cobalt Sollerets","l":48,"c":2140,"t":38}}]}