{"npc":{"name":"Storm Private","id":1007994,"patch":2.2,"zoneid":1161,"coords":[10.01,13.19],"areaid":1149,"appearance":{"gender":"Male","race":"Miqo'te","tribe":"Seeker of the Sun","height":50,"face":2,"jaw":1,"eyebrows":4,"nose":1,"skinColor":"13, 3","skinColorCode":"#C59C7D","hairStyle":134001,"hairColor":"3, 8","hairColorCode":"#514D41","eyeSize":"Large","eyeShape":2,"eyeColor":"3, 6","eyeColorCode":"#978764","mouth":1,"extraFeatureName":"Tail","extraFeatureShape":1,"extraFeatureSize":50},"equipment":[{"id":2716},{"id":3048},{"id":3566},{"id":3307,"uncertainty":6},{"id":3797}],"alts":[1005105,1005241,1005244,1008683,1008692,1013306,1013310,1014662,1026217,1026250,1026251]},"partials":[{"type":"item","id":"2716","obj":{"i":2716,"n":"Lominsan Soldier's Cap","l":21,"c":998,"t":34}},{"type":"item","id":"3048","obj":{"i":3048,"n":"Lominsan Soldier's Overcoat","l":21,"c":1317,"t":35}},{"type":"item","id":"3566","obj":{"i":3566,"n":"Lominsan Soldier's Gloves","l":21,"c":1815,"t":37}},{"type":"item","id":"3307","obj":{"i":3307,"n":"Hempen Underpants","l":1,"c":1568,"t":36,"p":39}},{"type":"item","id":"3797","obj":{"i":3797,"n":"Lominsan Soldier's Boots","l":21,"c":2036,"t":38}},{"type":"npc","id":"1005105","obj":{"i":1005105,"n":"Storm Private"}},{"type":"npc","id":"1005241","obj":{"i":1005241,"n":"Storm Private","l":358,"s":7,"t":"Disciple of Magic Arms Supplier","r":1}},{"type":"npc","id":"1005244","obj":{"i":1005244,"n":"Storm Private","l":358,"s":8,"t":"Disciple of War Armor Outfitter","r":1}},{"type":"npc","id":"1008683","obj":{"i":1008683,"n":"Storm Private","l":33,"q":1}},{"type":"npc","id":"1008692","obj":{"i":1008692,"n":"Storm Private","l":31,"q":1}},{"type":"npc","id":"1013306","obj":{"i":1013306,"n":"Storm Private","l":34,"q":1}},{"type":"npc","id":"1013310","obj":{"i":1013310,"n":"Storm Private","l":34,"q":1}},{"type":"npc","id":"1014662","obj":{"i":1014662,"n":"Storm Private","l":34,"q":1}},{"type":"npc","id":"1026217","obj":{"i":1026217,"n":"Storm Private"}},{"type":"npc","id":"1026250","obj":{"i":1026250,"n":"Storm Private","l":28}},{"type":"npc","id":"1026251","obj":{"i":1026251,"n":"Storm Private"}}]}