{"npc":{"name":"Cascadier Captain","id":1008137,"patch":2.0,"appearance":{"gender":"Female","race":"Roegadyn","tribe":"Sea Wolf","height":100,"face":4,"jaw":3,"eyebrows":4,"nose":3,"skinColor":"15, 4","skinColorCode":"#859D92","muscle":50,"bust":100,"hairStyle":135208,"hairColor":"12, 5","hairColorCode":"#84211A","highlightColor":"6, 3","highlightColorCode":"#FFBA56","eyeSize":"Small","eyeShape":5,"eyeColor":"8, 4","eyeColorCode":"#B87A34","mouth":4,"facialfeatures":[135342],"facialfeatureColor":"1, 1","facialfeatureColorCode":"#F7F7F7"},"equipment":[{"id":2834,"uncertainty":7},{"id":6096},{"id":6097},{"id":3764,"uncertainty":1}],"alts":[1008130,1008132]},"partials":[{"type":"item","id":"2834","obj":{"i":2834,"n":"Cobalt Preserves","l":44,"c":1110,"t":34,"p":4554}},{"type":"item","id":"6096","obj":{"i":6096,"n":"Striped Summer Top","l":1,"c":3624,"t":35,"p":59}},{"type":"item","id":"6097","obj":{"i":6097,"n":"Striped Summer Trunks","l":1,"c":3625,"t":36,"p":39}},{"type":"item","id":"3764","obj":{"i":3764,"n":"Leather Sandals","l":5,"c":2005,"t":38,"p":115}},{"type":"npc","id":"1008130","obj":{"i":1008130,"n":"Cascadier Captain"}},{"type":"npc","id":"1008132","obj":{"i":1008132,"n":"Cascadier Captain"}}]}