{"npc":{"name":"Ethelia","id":1009248,"patch":2.3,"title":"Moonfire Faire Chaperone","zoneid":31,"coords":[28.19,15.61],"areaid":202,"appearance":{"gender":"Female","race":"Hyur","tribe":"Midlander","height":50,"face":5,"jaw":1,"eyebrows":3,"nose":1,"skinColor":"20, 1","skinColorCode":"#F0CCB6","muscle":50,"bust":100,"hairStyle":131214,"hairColor":"4, 4","hairColorCode":"#F2C56D","highlightColor":"1, 1","highlightColorCode":"#F6F6F6","eyeSize":"Large","eyeShape":2,"eyeColor":"20, 2","eyeColorCode":"#7AA2B1","mouth":1,"lipShade":"Light","lipColor":"6, 2","lipColorCode":"#CF867F","facialfeatures":[131352],"facialfeatureColor":"1, 1","facialfeatureColorCode":"#F7F7F7"},"quests":[67073,67076],"talk":[{"lines":["Beating the heat─that's what any summer festival worth its salt offers participants, and the Moonfire Faire is no slouch. Here at the Rousing Douse event, refreshingly cool is the order of business!"]}],"equipment":[{"id":8532},{"id":3280},{"id":3748}],"alts":[1017248,1023796]},"partials":[{"type":"quest","id":"67073","obj":{"i":67073,"n":"Drench It! Moonfire Faire","g":120,"l":27,"s":45}},{"type":"quest","id":"67076","obj":{"i":67076,"n":"A Rousing Douse","g":120,"l":31,"s":48,"r":1}},{"type":"item","id":"8532","obj":{"i":8532,"n":"Lord's Yukata (Blackflame)","l":1,"c":5016,"t":35,"p":59}},{"type":"item","id":"3280","obj":{"i":3280,"n":"Lord's Drawers (Black)","l":1,"c":1541,"t":36,"p":45}},{"type":"item","id":"3748","obj":{"i":3748,"n":"Lord's Clogs","l":1,"c":1989,"t":38,"p":54}},{"type":"npc","id":"1017248","obj":{"i":1017248,"n":"Ethelia","l":32,"t":"Moonfire Faire Crier"}},{"type":"npc","id":"1023796","obj":{"i":1023796,"n":"Ethelia","l":32,"t":"Moonfire Faire Crier"}}]}