{"npc":{"name":"Mathye","id":1012181,"patch":3.0,"zoneid":2301,"coords":[6.27,9.43],"areaid":2317,"appearance":{"gender":"Male","race":"Hyur","tribe":"Midlander","height":50,"face":6,"jaw":4,"eyebrows":5,"nose":1,"skinColor":"18, 4","skinColorCode":"#B5886D","muscle":50,"hairStyle":131013,"hairColor":"5, 6","hairColorCode":"#80704C","eyeSize":"Large","eyeShape":4,"eyeColor":"21, 4","eyeColorCode":"#2B756A","mouth":2},"quests":[67265,67405,67611,67688,67689,67856],"talk":[{"lines":["I am but a humble merchant, my dear <span class=\"alternative-container\"><span class=\"alternative\">miss</span><span class=\"alternative\">sir</span></span>, but I pride myself on my selection. From folios for the scholasticate to chocobo fodder, I promise you I have it!"]}],"equipment":[{"id":11958,"dye":6,"uncertainty":1},{"id":15854,"dye":66,"uncertainty":1},{"id":11966,"uncertainty":1},{"id":9284},{"id":11981,"dye":5,"uncertainty":1}]},"partials":[{"type":"quest","id":"67265","obj":{"i":67265,"n":"Landing a Stable Job","g":59,"l":62,"s":5004}},{"type":"quest","id":"67405","obj":{"i":67405,"n":"Keeping the Ledger","g":42,"l":62,"s":1}},{"type":"quest","id":"67611","obj":{"i":67611,"n":"Turndown Service","g":87,"l":39,"s":502,"f":1}},{"type":"quest","id":"67688","obj":{"i":67688,"n":"Contradicting Convictions","g":42,"l":62,"s":10}},{"type":"quest","id":"67689","obj":{"i":67689,"n":"The Benefits of Consultation","g":42,"l":62,"s":11}},{"type":"quest","id":"67856","obj":{"i":67856,"n":"Tricks and Stones","g":37,"l":2002,"s":1,"f":1}},{"type":"item","id":"11958","obj":{"i":11958,"n":"Adept's Hat","l":130,"c":6883,"t":34}},{"type":"item","id":"15854","obj":{"i":15854,"n":"Alpine Coat","l":1,"c":8567,"t":35,"p":100}},{"type":"item","id":"11966","obj":{"i":11966,"n":"Holy Rainbow Gloves","l":80,"c":6891,"t":37,"p":7096}},{"type":"item","id":"9284","obj":{"i":9284,"n":"Best Man's Slacks","l":1,"c":5502,"t":36,"p":12000}},{"type":"item","id":"11981","obj":{"i":11981,"n":"Adept's Thighboots","l":130,"c":6905,"t":38}}]}