{"npc":{"name":"Black Ranger","id":1017223,"patch":3.0,"zoneid":32,"coords":[25.96,30.49],"areaid":209,"appearance":{"gender":"Female","race":"Hyur","tribe":"Highlander","height":100,"face":1,"customFace":1,"jaw":2,"eyebrows":2,"nose":3,"skinColor":"1, 1","skinColorCode":"#F9DAC1","muscle":100,"bust":100,"hairStyle":131726,"hairColor":"20, 3","hairColorCode":"#8DB0C0","highlightColor":"1, 8","highlightColorCode":"#050505","eyeSize":"Large","eyeShape":3,"eyeColor":"21, 3","eyeColorCode":"#3F8C83","mouth":2,"lipShade":"Dark","lipColor":"6, 3","lipColorCode":"#713533","facepaint":130123,"facepaintShade":"Dark","facepaintColor":"7, 4","facepaintColorCode":"#491D36","facialfeatures":[131812,131814],"facialfeatureColor":"1, 1","facialfeatureColorCode":"#F7F7F7"},"equipment":[{"id":7492,"dye":102},{"id":15468,"dye":102},{"id":15469,"dye":102},{"id":15470,"dye":102},{"id":15471,"dye":102}],"alts":[1017205,1017206,1017207,1017219,1017220,1017221,1017222,1017224,1017225,1017226,1017227,1017228,1017305]},"partials":[{"type":"item","id":"7492","obj":{"i":7492,"n":"Saurian Bandana of Striking","l":90,"c":4507,"t":34}},{"type":"item","id":"15468","obj":{"i":15468,"n":"Legacy Warrior Mail","l":1,"c":8680,"t":35,"p":156}},{"type":"item","id":"15469","obj":{"i":15469,"n":"Legacy Warrior Armguards","l":1,"c":8681,"t":37,"p":94}},{"type":"item","id":"15470","obj":{"i":15470,"n":"Legacy Warrior Breeches","l":1,"c":8682,"t":36,"p":156}},{"type":"item","id":"15471","obj":{"i":15471,"n":"Legacy Warrior Sabatons","l":1,"c":8683,"t":38,"p":94}},{"type":"npc","id":"1017205","obj":{"i":1017205,"n":"Black Ranger"}},{"type":"npc","id":"1017206","obj":{"i":1017206,"n":"Black Ranger"}},{"type":"npc","id":"1017207","obj":{"i":1017207,"n":"Black Ranger"}},{"type":"npc","id":"1017219","obj":{"i":1017219,"n":"Black Ranger","l":32}},{"type":"npc","id":"1017220","obj":{"i":1017220,"n":"Black Ranger","l":32}},{"type":"npc","id":"1017221","obj":{"i":1017221,"n":"Black Ranger","l":32}},{"type":"npc","id":"1017222","obj":{"i":1017222,"n":"Black Ranger","l":32}},{"type":"npc","id":"1017224","obj":{"i":1017224,"n":"Black Ranger","l":32}},{"type":"npc","id":"1017225","obj":{"i":1017225,"n":"Black Ranger","l":32}},{"type":"npc","id":"1017226","obj":{"i":1017226,"n":"Black Ranger","l":32}},{"type":"npc","id":"1017227","obj":{"i":1017227,"n":"Black Ranger","l":32}},{"type":"npc","id":"1017228","obj":{"i":1017228,"n":"Black Ranger","l":32}},{"type":"npc","id":"1017305","obj":{"i":1017305,"n":"Black Ranger","l":32}}]}