{"npc":{"name":"Nigen","id":1019387,"patch":4.0,"zoneid":2411,"coords":[32.02,11.6],"areaid":2821,"appearance":{"gender":"Female","race":"Au Ra","tribe":"Xaela","height":100,"face":3,"customFace":1,"jaw":3,"eyebrows":1,"nose":2,"skinColor":"20, 7","skinColorCode":"#202839","bust":0,"hairStyle":136246,"hairColor":"19, 5","hairColorCode":"#5D436B","highlightColor":"17, 6","highlightColorCode":"#432336","eyeSize":"Large","eyeShape":4,"eyeColor":"12, 3","eyeColorCode":"#B64D52","mouth":3,"lipShade":"Light","lipColor":"9, 8","lipColorCode":"#201927","extraFeatureName":"Tail","extraFeatureShape":2,"extraFeatureSize":50,"facepaint":130921,"facepaintShade":"Dark","facepaintColor":"9, 8","facepaintColorCode":"#0A0C18","facialfeatures":[136831,136834,136836,136837],"facialfeatureColor":"11, 7","facialfeatureColorCode":"#5E2419"},"tripletriad":{"fee":25,"cards":[9827,12275,20251,14195,16764,9816],"rules":["Same","Plus"],"quests":[68308],"rewards":[20251,20245]},"quests":[68302,68304,68308],"talk":[{"lines":["The gods said I should cook steak today, but they neglected to say if it should be rare, medium, or well-done..."]}],"equipment":[{"id":18469},{"id":19638,"dye":14},{"id":18453},{"id":18442},{"id":18473}]},"partials":[{"type":"item","id":"9827","obj":{"i":9827,"n":"Minfilia Card","l":1,"c":5781,"t":86}},{"type":"item","id":"12275","obj":{"i":12275,"n":"Bismarck Card","l":1,"c":5781,"t":86}},{"type":"item","id":"20251","obj":{"i":20251,"n":"Cirina Card","l":1,"c":5780,"t":86}},{"type":"item","id":"14195","obj":{"i":14195,"n":"Fenrir Card","l":1,"c":5780,"t":86}},{"type":"item","id":"16764","obj":{"i":16764,"n":"Strix Card","l":1,"c":5780,"t":86}},{"type":"item","id":"9816","obj":{"i":9816,"n":"Godbert Manderville Card","l":1,"c":5780,"t":86}},{"type":"quest","id":"68308","obj":{"i":68308,"n":"And Dzo It Goes","g":73,"l":2411,"s":5210}},{"type":"item","id":"20245","obj":{"i":20245,"n":"Mammoth Card","l":1,"c":5780,"t":86}},{"type":"quest","id":"68302","obj":{"i":68302,"n":"Absolute Faith","g":73,"l":2411,"s":5150}},{"type":"quest","id":"68304","obj":{"i":68304,"n":"Keeping the Faith","g":73,"l":2411,"s":5170}},{"type":"item","id":"18469","obj":{"i":18469,"n":"Nomad's Cap of Healing","l":276,"c":10414,"t":34}},{"type":"item","id":"19638","obj":{"i":19638,"n":"Kudzu Coat of Gathering","l":220,"c":9909,"t":35,"p":28749}},{"type":"item","id":"18453","obj":{"i":18453,"n":"Nomad's Armlets of Striking","l":276,"c":10427,"t":37}},{"type":"item","id":"18442","obj":{"i":18442,"n":"Nomad's Breeches of Fending","l":276,"c":10436,"t":36}},{"type":"item","id":"18473","obj":{"i":18473,"n":"Nomad's Boots of Healing","l":276,"c":10410,"t":38}}]}