{"npc":{"name":"Honoraint","id":1001142,"patch":1.0,"zoneid":52,"appearance":{"gender":"Male","race":"Elezen","tribe":"Wildwood","height":50,"face":2,"jaw":1,"eyebrows":1,"nose":1,"skinColor":"21, 3","skinColorCode":"#D19A81","hairStyle":132004,"hairColor":"2, 8","hairColorCode":"#4E4B3B","eyeSize":"Large","eyeShape":1,"eyeColor":"1, 5","eyeColorCode":"#878787","mouth":1,"extraFeatureName":"Ears","extraFeatureShape":1,"extraFeatureSize":50},"talk":[{"lines":["Ah! Give a man a bloody fright, sneakin' up on me like that...","Hm? Newly come to Gridania, are ye? Then I suggest ye continue on yer merry way to the Carline Canopy just behind me. Mother Miounne will want a word with ye."]}],"equipment":[{"id":10021},{"id":10022,"dye":18},{"id":10023},{"id":4308}],"alts":[1000122]},"partials":[{"type":"item","id":"10021","obj":{"i":10021,"n":"Tunique sombrelinçoise","l":1,"c":5803,"t":35}},{"type":"item","id":"10022","obj":{"i":10022,"n":"Trousses sombrelinçoises","l":1,"c":5804,"t":36}},{"type":"item","id":"10023","obj":{"i":10023,"n":"Chaussures sombrelinçoises","l":1,"c":5805,"t":38}},{"type":"item","id":"4308","obj":{"i":4308,"n":"Ras de cou en cuir rigide","l":15,"c":2459,"t":40,"p":294}},{"type":"npc","id":"1000122","obj":{"i":1000122,"n":"Honoraint","l":52,"q":1,"k":1}}]}