{"npc":{"name":"Admirateur De Yellow Moon","id":1005596,"patch":2.1,"zoneid":40,"coords":[10.3,8.76],"areaid":642,"appearance":{"gender":"Male","race":"Hyur","tribe":"Highlander","height":0,"face":1,"jaw":2,"eyebrows":3,"nose":2,"skinColor":"7, 3","skinColorCode":"#C7A789","muscle":50,"hairStyle":131502,"hairColor":"23, 5","hairColorCode":"#5B6E5B","eyeSize":"Large","eyeShape":3,"eyeColor":"3, 6","eyeColorCode":"#978764","mouth":3},"equipment":[{"id":2665,"dye":38},{"id":3109,"dye":38,"uncertainty":1},{"id":3576,"dye":6},{"id":3309},{"id":3762},{"id":4220}],"alts":[1005593,1005594,1005595,1005597,1005598,1005618]},"partials":[{"type":"item","id":"2665","obj":{"i":2665,"n":"Turban en coton","l":12,"c":950,"t":34,"p":282}},{"type":"item","id":"3109","obj":{"i":3109,"n":"Tunique de soldat des Deux Vipères","l":32,"c":1375,"t":35}},{"type":"item","id":"3576","obj":{"i":3576,"n":"Gants sans doigts en cuir de bouquetin","l":25,"c":1824,"t":37,"p":1282}},{"type":"item","id":"3309","obj":{"i":3309,"n":"Chausses","l":5,"c":1570,"t":36,"p":94}},{"type":"item","id":"3762","obj":{"i":3762,"n":"Souliers à poulaine","l":5,"c":2003,"t":38,"p":115}},{"type":"item","id":"4220","obj":{"i":4220,"n":"Boucles d'oreilles de sphènes","l":29,"c":2390,"t":41,"p":2544}},{"type":"npc","id":"1005593","obj":{"i":1005593,"n":"Admirateur De Yellow Moon","l":373}},{"type":"npc","id":"1005594","obj":{"i":1005594,"n":"Admirateur De Yellow Moon","l":373}},{"type":"npc","id":"1005595","obj":{"i":1005595,"n":"Admirateur De Yellow Moon","l":40}},{"type":"npc","id":"1005597","obj":{"i":1005597,"n":"Admirateur De Yellow Moon","l":373}},{"type":"npc","id":"1005598","obj":{"i":1005598,"n":"Admirateur De Yellow Moon","l":373}},{"type":"npc","id":"1005618","obj":{"i":1005618,"n":"Admirateur De Yellow Moon"}}]}