{"npc":{"name":"Sergente Instructrice Du Maelstrom","id":1005418,"patch":3.4,"zoneid":358,"coords":[6.83,5.78],"areaid":1794,"appearance":{"gender":"Female","race":"Roegadyn","tribe":"Sea Wolf","height":100,"face":2,"jaw":3,"eyebrows":3,"nose":5,"skinColor":"22, 5","skinColorCode":"#828683","muscle":25,"bust":75,"hairStyle":135236,"hairColor":"4, 5","hairColorCode":"#C3A66F","highlightColor":"6, 6","highlightColorCode":"#916C37","eyeSize":"Large","eyeShape":5,"eyeColor":"10, 5","eyeColorCode":"#934826","mouth":3,"lipShade":"Dark","lipColor":"6, 5","lipColorCode":"#531818","facialfeatures":[135321,135322],"facialfeatureColor":"1, 1","facialfeatureColorCode":"#F7F7F7"},"quests":[67929],"equipment":[{"id":3246},{"id":3703},{"id":3307,"uncertainty":6},{"id":3924}]},"partials":[{"type":"quest","id":"67929","obj":{"i":67929,"n":"Duel sur la jetée","g":54,"l":358,"s":0}},{"type":"item","id":"3246","obj":{"i":3246,"n":"Casaque d'officier du Maelstrom","l":55,"c":1508,"t":35}},{"type":"item","id":"3703","obj":{"i":3703,"n":"Gants d'officier du Maelstrom","l":55,"c":1945,"t":37}},{"type":"item","id":"3307","obj":{"i":3307,"n":"Haut-de-chausses","l":1,"c":1568,"t":36,"p":39}},{"type":"item","id":"3924","obj":{"i":3924,"n":"Bottes d'officier du Maelstrom","l":55,"c":2156,"t":38}}]}