{"npc":{"name":"Nenekko","id":1010368,"patch":2.4,"appearance":{"gender":"Female","race":"Lalafell","tribe":"Dunesfolk","height":25,"face":2,"jaw":2,"eyebrows":4,"nose":3,"skinColor":"13, 3","skinColorCode":"#CBA284","bust":50,"hairStyle":133204,"hairColor":"10, 5","hairColorCode":"#B86624","eyeSize":"Large","eyeShape":4,"eyeColor":"13, 4","eyeColorCode":"#942C48","mouth":4,"extraFeatureName":"Ears","extraFeatureShape":1,"extraFeatureSize":50},"equipment":[{"id":2530},{"id":2886,"uncertainty":1},{"id":10053,"uncertainty":1},{"id":13693,"uncertainty":1},{"id":13691,"uncertainty":1},{"id":13692,"uncertainty":1}],"alts":[1007203,1010367,1011681]},"partials":[{"type":"item","id":"2530","obj":{"i":2530,"n":"Dolabre à aigrette","l":48,"c":840,"t":28,"p":6933}},{"type":"item","id":"2886","obj":{"i":2886,"n":"Béret en feutre","l":48,"c":1161,"t":34}},{"type":"item","id":"10053","obj":{"i":10053,"n":"Peignoir de façonnier","l":70,"c":5722,"t":35}},{"type":"item","id":"13693","obj":{"i":13693,"n":"Mitaines de Thancred","l":1,"c":7874,"t":37}},{"type":"item","id":"13691","obj":{"i":13691,"n":"Chausses de Y'shtola","l":1,"c":7872,"t":36}},{"type":"item","id":"13692","obj":{"i":13692,"n":"Patins de Y'shtola","l":1,"c":7873,"t":38}},{"type":"npc","id":"1007203","obj":{"i":1007203,"n":"Nenekko"}},{"type":"npc","id":"1010367","obj":{"i":1010367,"n":"Nenekko"}},{"type":"npc","id":"1011681","obj":{"i":1011681,"n":"Nenekko","l":40,"q":1}}]}