{"npc":{"name":"Homme De Main","id":1010434,"patch":2.51,"zoneid":34,"coords":[26.34,26.65],"areaid":241,"appearance":{"gender":"Male","race":"Roegadyn","tribe":"Sea Wolf","height":50,"face":3,"jaw":1,"eyebrows":4,"nose":3,"skinColor":"5, 7","skinColorCode":"#55584D","muscle":100,"hairStyle":135004,"hairColor":"6, 6","hairColorCode":"#916A39","highlightColor":"22, 3","highlightColorCode":"#759E79","eyeSize":"Small","eyeShape":3,"eyeColor":"8, 2","eyeColorCode":"#E1B27C","mouth":1,"facepaint":130643,"facepaintShade":"Dark","facepaintColor":"6, 6","facepaintColorCode":"#460E0D","facialfeatures":[135131,135132,135134,135135,135136],"facialfeatureColor":"1, 8","facialfeatureColorCode":"#262626"},"quests":[65779],"equipment":[{"id":10598,"uncertainty":1},{"id":3174,"dye":33},{"id":6836,"uncertainty":18},{"id":3439,"uncertainty":1},{"id":3900,"uncertainty":1},{"id":4491},{"id":4439}]},"partials":[{"type":"quest","id":"65779","obj":{"i":65779,"n":"Une guéguerre de clic clic","g":48,"l":27,"s":20}},{"type":"item","id":"10598","obj":{"i":10598,"n":"Hache de guerre en mithrite","l":115,"c":6082,"t":3,"p":22587}},{"type":"item","id":"3174","obj":{"i":3174,"n":"Haubergeon en mithril","l":43,"c":1437,"t":35}},{"type":"item","id":"6836","obj":{"i":6836,"n":"Canons d'avant-bras d'abatteur de loup combattant","l":70,"c":4135,"t":37}},{"type":"item","id":"3439","obj":{"i":3439,"n":"Saroual de sergent des Immortels","l":46,"c":1690,"t":36}},{"type":"item","id":"3900","obj":{"i":3900,"n":"Souliers à poulaine de sipahi","l":55,"c":2134,"t":38}},{"type":"item","id":"4491","obj":{"i":4491,"n":"Bague de récolteur du Maelstrom","l":47,"c":2609,"t":43}},{"type":"item","id":"4439","obj":{"i":4439,"n":"Bague en argent","l":27,"c":2567,"t":43,"p":1254}}]}