{"npc":{"name":"Ysaudore","id":1011903,"patch":3.0,"zoneid":2200,"coords":[26.53,28.0],"areaid":2216,"appearance":{"gender":"Female","race":"Elezen","tribe":"Wildwood","height":50,"face":4,"jaw":1,"eyebrows":2,"nose":4,"skinColor":"3, 2","skinColorCode":"#EECBAF","bust":50,"hairStyle":132206,"hairColor":"10, 3","hairColorCode":"#DD9B75","eyeSize":"Large","eyeShape":4,"eyeColor":"9, 7","eyeColorCode":"#653616","mouth":1,"lipShade":"Light","lipColor":"7, 3","lipColorCode":"#A13E67","extraFeatureName":"Ears","extraFeatureShape":1,"extraFeatureSize":50,"facepaint":130202,"facepaintShade":"Dark","facepaintColor":"6, 2","facepaintColorCode":"#875351"},"quests":[67122,67271],"talk":[{"lines":["Nothing out of the ordinary so far...but who can say what the <span class=\"alternative-container\"><span class=\"alternative\">morning</span><span class=\"alternative\">day</span><span class=\"alternative\">evening</span></span> will bring."]}],"equipment":[{"id":6824,"uncertainty":2},{"id":6722,"uncertainty":10},{"id":6716},{"id":14034,"uncertainty":2}]},"partials":[{"type":"quest","id":"67122","obj":{"i":67122,"n":"Amour interdit","g":3,"l":2200,"s":7}},{"type":"quest","id":"67271","obj":{"i":67271,"n":"Dans la gueule du loup","g":57,"l":2200,"s":5002}},{"type":"item","id":"6824","obj":{"i":6824,"n":"Haubergeon d'abatteur de loup combattant","l":70,"c":4125,"t":35}},{"type":"item","id":"6722","obj":{"i":6722,"n":"Canons d'avant-bras épais","l":60,"c":4100,"t":37}},{"type":"item","id":"6716","obj":{"i":6716,"n":"Jupe épaisse","l":60,"c":4095,"t":36}},{"type":"item","id":"14034","obj":{"i":14034,"n":"Sabatons de novice","l":17,"c":7910,"t":38}}]}