{"mob":{"name":"Hrodric Giftzunge","id":81100000006910,"quest":1,"zoneid":2367,"lvl":"70","drops":[20820,20826,20832,20844,20838,20856,20850,20822,20828,20834,20846,20840,20858,20852,21193,21288],"instance":58},"partials":[{"type":"item","id":"20820","obj":{"i":20820,"n":"Skalla-Mantel der Verteidigung","l":315,"c":11409,"t":35}},{"type":"item","id":"20826","obj":{"i":20826,"n":"Skalla-Mantel des Verstümmelns","l":315,"c":11404,"t":35}},{"type":"item","id":"20832","obj":{"i":20832,"n":"Skalla-Jacke des Schlagens","l":315,"c":11399,"t":35}},{"type":"item","id":"20844","obj":{"i":20844,"n":"Skalla-Brustpanzer des Schurken","l":315,"c":11389,"t":35}},{"type":"item","id":"20838","obj":{"i":20838,"n":"Skalla-Jacke des Zielens","l":315,"c":11394,"t":35}},{"type":"item","id":"20856","obj":{"i":20856,"n":"Skalla-Jacke der Magie","l":315,"c":11379,"t":35}},{"type":"item","id":"20850","obj":{"i":20850,"n":"Skalla-Jacke der Heilung","l":315,"c":11384,"t":35}},{"type":"item","id":"20822","obj":{"i":20822,"n":"Skalla-Hose der Verteidigung","l":315,"c":11407,"t":36}},{"type":"item","id":"20828","obj":{"i":20828,"n":"Skalla-Hose des Verstümmelns","l":315,"c":11402,"t":36}},{"type":"item","id":"20834","obj":{"i":20834,"n":"Skalla-Hose des Schlagens","l":315,"c":11397,"t":36}},{"type":"item","id":"20846","obj":{"i":20846,"n":"Skalla-Sarouel des Schurken","l":315,"c":11387,"t":36}},{"type":"item","id":"20840","obj":{"i":20840,"n":"Skalla-Hose des Zielens","l":315,"c":11392,"t":36}},{"type":"item","id":"20858","obj":{"i":20858,"n":"Skalla-Sarouel der Magie","l":315,"c":11377,"t":36}},{"type":"item","id":"20852","obj":{"i":20852,"n":"Skalla-Hose der Heilung","l":315,"c":11382,"t":36}},{"type":"item","id":"21193","obj":{"i":21193,"n":"Gomashio-Seehund","l":1,"c":11260,"t":81}},{"type":"item","id":"21288","obj":{"i":21288,"n":"Notenrolle von „Far From Home“","l":1,"c":7977,"t":94}},{"type":"instance","id":"58","obj":{"i":58,"n":"Die versunkene Stadt Skalla","c":61801,"t":"Dungeons","min_lvl":70,"max_lvl":70,"min_ilvl":300,"max_ilvl":370}}]}