{"instance":{"name":"Die Ghimlyt-Finsternis","category":"Dungeons","description":"Die Kontinente Aldenard und Ilsabard sind durch die Ghimlyt-Landbrücke verbunden, welche aufgrund geografischer Besonderheiten und ätherischer Phänomene in eine dauernde, lebensfeindliche Lichtlosigkeit getaucht ist: die Ghimlyt-Finsternis.\r\nHierhin hat sich nach der Befreiung von Ala Mhigo die Grenze zwischen der Eorzäischen Allianz und dem Garleischen Kaiserreich verlagert, und hier lässt Kaiser Varis nun seine Legionen aufmarschieren, um die Länder des Westens zu unterjochen. Mutig werfen sich Truppen aus allen Staaten Eorzeas den Invasoren entgegen!","id":64,"patch":4.5,"categoryIcon":61801,"time":90,"min_lvl":70,"fullIcon":112333,"healer":1,"tank":1,"ranged":1,"melee":1,"max_lvl":70,"min_ilvl":360,"unlockedByQuest":68719},"partials":[{"type":"quest","id":"68719","obj":{"i":68719,"n":"Grenzschlacht","g":7,"l":2742,"s":38}}]}