{"npc":{"name":"帝国軍幕僚","id":1007038,"patch":2.0,"appearance":{"gender":"Male","race":"Elezen","tribe":"Wildwood","height":50,"face":1,"jaw":1,"eyebrows":4,"nose":1,"skinColor":"13, 3","skinColorCode":"#CDA584","hairStyle":132010,"hairColor":"3, 8","hairColorCode":"#444336","eyeSize":"Large","eyeShape":2,"eyeColor":"3, 6","eyeColorCode":"#978764","mouth":1,"extraFeatureName":"Ears","extraFeatureShape":1,"extraFeatureSize":50},"equipment":[{"id":15181,"uncertainty":1},{"id":2293}],"alts":[1018482]},"partials":[{"type":"item","id":"15181","obj":{"i":15181,"n":"パジャルブレード","l":235,"c":8584,"t":2}},{"type":"item","id":"2293","obj":{"i":2293,"n":"ウォーロックバックラー","l":49,"c":688,"t":11}},{"type":"npc","id":"1018482","obj":{"i":1018482,"n":"帝国軍の将校"}}]}