{"npc":{"name":"街人D","id":1007201,"patch":2.0,"appearance":{"gender":"Male","race":"Roegadyn","tribe":"Sea Wolf","height":50,"face":3,"jaw":3,"eyebrows":1,"nose":3,"skinColor":"6, 3","skinColorCode":"#BDCEB6","muscle":50,"hairStyle":135011,"hairColor":"1, 4","hairColorCode":"#9C9C9C","eyeSize":"Small","eyeShape":4,"eyeColor":"1, 4","eyeColorCode":"#B3B3B3","mouth":1},"equipment":[{"id":2546},{"id":2652,"uncertainty":1},{"id":11989,"uncertainty":19},{"id":3588},{"id":12002,"uncertainty":1},{"id":3872,"uncertainty":1}]},"partials":[{"type":"item","id":"2546","obj":{"i":2546,"n":"ハチェット","l":8,"c":849,"t":30,"p":257}},{"type":"item","id":"2652","obj":{"i":2652,"n":"バンダナ","l":5,"c":937,"t":34,"p":85}},{"type":"item","id":"11989","obj":{"i":11989,"n":"ワイバーンジャーキン","l":80,"c":6913,"t":35,"p":12355}},{"type":"item","id":"3588","obj":{"i":3588,"n":"グリダニアンプライベート・ブレーサー","l":29,"c":1835,"t":37}},{"type":"item","id":"12002","obj":{"i":12002,"n":"ワイバーンキュロット","l":80,"c":6923,"t":36,"p":9504}},{"type":"item","id":"3872","obj":{"i":3872,"n":"グリダニアンサージェント・モカシン","l":44,"c":2107,"t":38}}]}