{"npc":{"name":"ダンスマスター","id":1010461,"patch":2.51,"title":"GATE Client","appearance":{"gender":"Female","race":"Roegadyn","tribe":"Hellsguard","height":0,"face":3,"jaw":1,"eyebrows":2,"nose":3,"skinColor":"22, 2","skinColorCode":"#C1AAA7","muscle":50,"bust":100,"hairStyle":135224,"hairColor":"23, 5","hairColorCode":"#5B6E5B","eyeSize":"Large","eyeShape":1,"eyeColor":"19, 3","eyeColorCode":"#516997","mouth":1,"lipShade":"Light","lipColor":"6, 5","lipColorCode":"#8B372E","facepaint":130761,"facepaintShade":"Dark","facepaintColor":"1, 8","facepaintColorCode":"#000000"},"equipment":[{"id":2996,"dye":6},{"id":13693,"uncertainty":1},{"id":7537,"dye":68},{"id":9046,"dye":6}],"alts":[1010453,1010455,1010457,1010459,1010463,1011592]},"partials":[{"type":"item","id":"2996","obj":{"i":2996,"n":"アンダーシャツ","l":1,"c":1269,"t":35,"p":59}},{"type":"item","id":"13693","obj":{"i":13693,"n":"サイオンズシーフ・ハーフグローブ","l":1,"c":7874,"t":37}},{"type":"item","id":"7537","obj":{"i":7537,"n":"セーラーブレー","l":1,"c":4544,"t":36}},{"type":"item","id":"9046","obj":{"i":9046,"n":"キリムストライカーサンダル","l":110,"c":5333,"t":38}},{"type":"npc","id":"1010453","obj":{"i":1010453,"n":"ダンスマスター","t":"GATE Client"}},{"type":"npc","id":"1010455","obj":{"i":1010455,"n":"ダンスマスター","t":"GATE Client"}},{"type":"npc","id":"1010457","obj":{"i":1010457,"n":"ダンスマスター","t":"GATE Client"}},{"type":"npc","id":"1010459","obj":{"i":1010459,"n":"ダンスマスター","t":"GATE Client"}},{"type":"npc","id":"1010463","obj":{"i":1010463,"n":"ダンスマスター","t":"GATE Client"}},{"type":"npc","id":"1011592","obj":{"i":1011592,"n":"ダンスマスター","t":"GATE Client"}}]}