{"npc":{"name":"アベリナ","id":1011024,"patch":2.51,"zoneid":1484,"coords":[4.98,7.32],"areaid":1487,"appearance":{"gender":"Female","race":"Hyur","tribe":"Midlander","height":100,"face":5,"jaw":1,"eyebrows":1,"nose":1,"skinColor":"19, 2","skinColorCode":"#E0BBA2","muscle":50,"bust":50,"hairStyle":131214,"hairColor":"14, 3","hairColorCode":"#BB748A","highlightColor":"13, 4","highlightColorCode":"#8C3033","eyeSize":"Large","eyeShape":2,"eyeColor":"20, 2","eyeColorCode":"#7AA2B1","mouth":4,"lipShade":"Light","lipColor":"7, 3","lipColorCode":"#A13E67","facialfeatures":[131352],"facialfeatureColor":"1, 1","facialfeatureColorCode":"#F7F7F7"},"quests":[67669],"talk":[{"lines":["Welcome to the Gold Saucer, honored guest. There's no end to the wonders within these halls─pray don't be shy about partaking in them!"]}],"equipment":[{"id":10009},{"id":10010},{"id":10011},{"id":10012},{"id":10013}]},"partials":[{"type":"quest","id":"67669","obj":{"i":67669,"n":"ゴールドソーサーの新たな催し","g":119,"l":1484,"s":106,"r":1}},{"type":"item","id":"10009","obj":{"i":10009,"n":"バニークラウン","l":1,"c":5791,"t":34}},{"type":"item","id":"10010","obj":{"i":10010,"n":"バニービスチェ","l":1,"c":5792,"t":35}},{"type":"item","id":"10011","obj":{"i":10011,"n":"バニーリストドレス","l":1,"c":5793,"t":37}},{"type":"item","id":"10012","obj":{"i":10012,"n":"バニータイツ","l":1,"c":5794,"t":36}},{"type":"item","id":"10013","obj":{"i":10013,"n":"バニーパンプス","l":1,"c":5795,"t":38}}]}