{"npc":{"name":"ジャ・ルダバ","id":1016960,"patch":3.0,"appearance":{"gender":"Female","race":"Miqo'te","tribe":"Seeker of the Sun","height":25,"face":3,"jaw":1,"eyebrows":4,"nose":1,"skinColor":"16, 2","skinColorCode":"#E0B79B","bust":75,"hairStyle":134204,"hairColor":"20, 6","hairColorCode":"#1F3563","highlightColor":"21, 3","highlightColorCode":"#608887","eyeSize":"Large","eyeShape":4,"eyeColor":"12, 3","eyeColorCode":"#B64D52","mouth":1,"extraFeatureName":"Tail","extraFeatureShape":5,"extraFeatureSize":75},"equipment":[{"id":2166},{"id":3219},{"id":3555},{"id":3476},{"id":3824}]},"partials":[{"type":"item","id":"2166","obj":{"i":2166,"n":"ブック・オブ・シルバー","l":34,"c":571,"t":10,"p":5515}},{"type":"item","id":"3219","obj":{"i":3219,"n":"ハーレクインアクトン","l":46,"c":1481,"t":35}},{"type":"item","id":"3555","obj":{"i":3555,"n":"アコライトハーフグローブ","l":17,"c":1804,"t":37}},{"type":"item","id":"3476","obj":{"i":3476,"n":"ハーレクインタイツ","l":46,"c":1727,"t":36}},{"type":"item","id":"3824","obj":{"i":3824,"n":"トーチャーダックビル","l":26,"c":2062,"t":38}}]}