{"npc":{"name":"屈強な冒険者","id":1017083,"patch":3.2,"zoneid":2082,"coords":[7.4,6.1],"areaid":2087,"appearance":{"gender":"Male","race":"Roegadyn","tribe":"Sea Wolf","height":0,"face":2,"jaw":3,"eyebrows":4,"nose":6,"skinColor":"5, 7","skinColorCode":"#55584D","muscle":50,"hairStyle":135040,"hairColor":"6, 5","hairColorCode":"#BA8948","eyeSize":"Large","eyeShape":1,"eyeColor":"21, 3","eyeColorCode":"#3F8C83","mouth":3,"facepaint":130641,"facepaintShade":"Dark","facepaintColor":"1, 8","facepaintColorCode":"#000000"},"quests":[67654],"equipment":[{"id":14722},{"id":14723},{"id":14724},{"id":14725},{"id":14726},{"id":11745},{"id":11750},{"id":12397},{"id":11035},{"id":11035}]},"partials":[{"type":"quest","id":"67654","obj":{"i":67654,"n":"不屈なアイツを討ち倒せ","g":64,"l":2082,"s":6000,"f":1}},{"type":"item","id":"14722","obj":{"i":14722,"n":"イコンレザー・ストライカーヘッドギア","l":220,"c":8159,"t":34}},{"type":"item","id":"14723","obj":{"i":14723,"n":"イコンレザー・ストライカーコースリット","l":220,"c":8160,"t":35}},{"type":"item","id":"14724","obj":{"i":14724,"n":"イコンレザー・ストライカーアームガード","l":220,"c":8161,"t":37}},{"type":"item","id":"14725","obj":{"i":14725,"n":"イコンクロス・ストライカーブレー","l":220,"c":8162,"t":36}},{"type":"item","id":"14726","obj":{"i":14726,"n":"イコンレザー・ストライカーレッグガード","l":220,"c":8163,"t":38}},{"type":"item","id":"11745","obj":{"i":11745,"n":"アーデントイヤリング・オブ・ディフェンス","l":200,"c":7463,"t":41}},{"type":"item","id":"11750","obj":{"i":11750,"n":"アーデントチョーカー・オブ・ディフェンス","l":200,"c":7464,"t":40}},{"type":"item","id":"12397","obj":{"i":12397,"n":"オーソドックス・ディフェンダーブレスレット","l":136,"c":7026,"t":42}},{"type":"item","id":"11035","obj":{"i":11035,"n":"クリソライトレンジャーリング","l":150,"c":6395,"t":43}}]}